mypykaizen/__init__.py
mypykaizen/mypykaizen.py
mypykaizen-0.17.0.dist-info/LICENSE
mypykaizen-0.17.0.dist-info/METADATA
mypykaizen-0.17.0.dist-info/WHEEL
mypykaizen-0.17.0.dist-info/entry_points.txt
mypykaizen-0.17.0.dist-info/top_level.txt
mypykaizen-0.17.0.dist-info/zip-safe
mypykaizen-0.17.0.dist-info/RECORD
